LICENSE.txt
MANIFEST.in
README.rst
changelog.txt
setup.py
POSST/Preparation.py
POSST/__init__.py
POSST/utils.py
POSST.egg-info/PKG-INFO
POSST.egg-info/SOURCES.txt
POSST.egg-info/dependency_links.txt
POSST.egg-info/not-zip-safe
POSST.egg-info/requires.txt
POSST.egg-info/top_level.txt