Metadata-Version: 1.0
Name: POSST
Version: 0.1.1
Summary: Module for the POSST project
Home-page: https://github.com/tognotommy/POSST
Author: Matteo Caruso, Tommaso Tognozzi
Author-email: matteo1.caruso@mail.polimi.it, tommaso.tognozzi@mail.polimi.it
License: MIT
Platform: UNKNOWN
